asteval/__init__.py
asteval/asteval.py
asteval/astutils.py
asteval/version.py
asteval-1.0.5.dist-info/LICENSE
asteval-1.0.5.dist-info/METADATA
asteval-1.0.5.dist-info/WHEEL
asteval-1.0.5.dist-info/top_level.txt
asteval-1.0.5.dist-info/RECORD
