Metadata-Version: 2.1
Name: asteval
Version: 1.0.5
Summary: Safe, minimalistic evaluator of python expression using ast module
Author-email: Matthew Newville <matt.newville@gmail.com>
License: The MIT License
Project-URL: Homepage,  https://github.com/lmfit/asteval
Project-URL: Documentation, https://lmfit.github.io/asteval/
Project-URL: Tracker, https://github.com/lmfit/asteval/issues
Keywords: AST,expression evaluation,eval
Classifier: Development Status :: 5 - Production/Stable
Classifier: Intended Audience :: Developers
Classifier: License :: OSI Approved :: MIT License
Classifier: Operating System :: OS Independent
Classifier: Programming Language :: Python :: 3.8
Classifier: Programming Language :: Python :: 3.9
Classifier: Programming Language :: Python :: 3.10
Classifier: Programming Language :: Python :: 3.11
Classifier: Programming Language :: Python :: 3.12
Classifier: Programming Language :: Python :: Implementation :: PyPy
Requires-Python: >=3.8
License-File: LICENSE
Provides-Extra: dev
Requires-Dist: build; extra == "dev"
Requires-Dist: twine; extra == "dev"
Provides-Extra: doc
Requires-Dist: Sphinx; extra == "doc"
Provides-Extra: test
Requires-Dist: pytest; extra == "test"
Requires-Dist: pytest-cov; extra == "test"
Requires-Dist: coverage; extra == "test"
Provides-Extra: all
Requires-Dist: asteval[dev,doc,test]; extra == "all"
